{"appId":"w:alagrede.znote","appShortcutName":"znote","appDisplayName":"znote","authorId":"w:winget","releaseTagName":"winget-3.6.10","downloadUrls":{"0":{"installerType":"WindowsInstallerMsi","asset":"","url":""},"1":{"installerType":"WindowsInstallerMsi","asset":"","url":""}},"install":{"win32":null,"winarm":null,"linux":null,"linuxArm64":null,"linuxArm7":null,"android":null},"displayImages":[],"description":"Markdown-based note-taking app for developers\n\n\n🚀 Release Notes\nThis release improves navigation, content referencing, and overall reliability, making Znote smoother and more powerful for building notes as tools.\n✨ Features\n- Improved menu UI for a cleaner, more consistent experience\n- Right-click on folders to create or delete folders\n- Enhanced Treeview behavior (better expand/collapse handling)\n- Reference blocks by name inside Quotes\n- Reference .txt and .md files in Quotes and AI inputs\n🐛 Fixes\n- Reveal in Treeview now works for notes in Trash\n- Emptying Trash automatically closes deleted notes\n- Fixed Ctrl+Y to properly open the note explorer in the editor\n- Fixed multi-line paste inside Quotes\n- Improved reliability of AI web search retries","repo":{"author":"microsoft","repo":"winget-pkgs"},"usrVersion":"3.6.10","version":0,"site":"https://github.com/alagrede","source":"alagrede","license_or_tos":"Freeware","resources":null,"verified":false}