{"appId":"w:BrowserStack.BrowserStackLocal","appShortcutName":"BrowserStackLocal","appDisplayName":"BrowserStackLocal","authorId":"w:winget","releaseTagName":"winget-3.7.1","downloadUrls":{"1":{"installerType":"WindowsInstallerMsi","asset":"","url":"https://www.browserstack.com/local-testing/downloads/native-app/BrowserStackLocal.msi"},"0":{"installerType":"WindowsInstallerMsi","asset":"","url":""}},"install":{"win32":{"assetId":1,"exec":null,"scope":"Machine","installerArgs":null},"winarm":null,"linux":null,"linuxArm64":null,"linuxArm7":null,"android":null},"displayImages":[],"description":"Local Testing lets you test work-in-progress web and mobile apps at scale without hosting them on public staging environments.\n\n\n","repo":{"author":"microsoft","repo":"winget-pkgs"},"usrVersion":"3.7.1","version":0,"site":"https://www.browserstack.com/","source":"BrowserStack","license_or_tos":"Proprietary","resources":null,"verified":false}