{"appId":"w:CHIRPSoftware.CHIRP_next","appShortcutName":"CHIRP-next","appDisplayName":"CHIRP-next","authorId":"w:winget","releaseTagName":"winget-20260123","downloadUrls":{"1":{"installerType":"WindowsInstallerExe","asset":"","url":"https://archive.chirpmyradio.com/chirp_next/next-20260123/chirp-next-20260123-installer.exe"},"0":{"installerType":"WindowsInstallerMsi","asset":"","url":""}},"install":{"win32":{"assetId":1,"exec":null,"scope":"Machine","installerArgs":null},"winarm":null,"linux":null,"linuxArm64":null,"linuxArm7":null,"android":null},"displayImages":[],"description":"The next-generation version of CHIRP, a free, open-source tool for programming your amateur radio that supports a large number of manufacturers and models.\n\n\n","repo":{"author":"microsoft","repo":"winget-pkgs"},"usrVersion":"20260123","version":0,"site":null,"source":"CHIRP Software LLC","license_or_tos":"GPL-3.0-only","resources":null,"verified":false}