{"appId":"w:EQAditu.AdvancedCombatTracker","appShortcutName":"Winget Application","appDisplayName":"Advanced Combat Tracker","authorId":"w:winget","releaseTagName":"winget-3.8.3.286","downloadUrls":{"1":{"installerType":"WindowsInstallerMsi","asset":"","url":""},"0":{"installerType":"WindowsInstallerMsi","asset":"","url":""}},"install":{"win32":null,"winarm":null,"linux":null,"linuxArm64":null,"linuxArm7":null,"android":null},"displayImages":[],"description":"A real-time MMO log parser.\n\n\nMiscellaneous / UI\nThe Custom Triggers and Spell Timers treeviews should remember node expansion between sessions; misc blind fixes.\nPlugins / API\nWizard downloads in general no longer use WININET caching nor temporary files. UnZip() no longer uses random filenames for temporary files. Temporary ZIP filenames may have numbers/symbols removed. UnZip() now has an overload that accepts a byte array instead of a file location. Added PluginDownloadMem() which returns a download as a byte array instead of a temporary file location.","repo":{"author":"microsoft","repo":"winget-pkgs"},"version":"3.8.3.286","site":"https://advancedcombattracker.com/","source":"EQAditu","license_or_tos":"Proprietary","resources":null,"verified":false}