{"appId":"w:GiantPinkRobots.Varia","appShortcutName":"Varia","appDisplayName":"Varia","authorId":"w:winget","releaseTagName":"winget-2025.10.14-1","downloadUrls":{"0":{"installerType":"WindowsInstallerMsi","asset":"","url":""},"1":{"installerType":"WindowsInstallerExe","asset":"","url":"https://github.com/giantpinkrobots/varia/releases/download/v2025.10.14-1/varia-windows-setup-amd64.exe"}},"install":{"win32":{"assetId":1,"exec":null,"scope":"Machine","installerArgs":null},"winarm":null,"linux":null,"linuxArm64":null,"linuxArm7":null,"android":null},"displayImages":[],"description":"Download manager based on aria2.\n\nVaria is a simple download manager. It uses the amazing aria2 to handle the downloads.\nIt supports basic functionality like continuing incomplete downloads from the previous session upon startup, pausing/cancelling all downloads at once, setting a speed limit, authentication with a username/password, setting the simultaneous download amount and setting the download directory.\n- Minor bugfix and translations update.","repo":{"author":"microsoft","repo":"winget-pkgs"},"usrVersion":"2025.10.14-1","version":0,"site":"https://github.com/giantpinkrobots","source":"Giant Pink Robots!","license_or_tos":"MPL-2.0","resources":null,"verified":false}