{"appId":"w:GitHub.cli","appShortcutName":"GitHub CLI","appDisplayName":"GitHub CLI","authorId":"w:winget","releaseTagName":"winget-2.88.1","downloadUrls":{"0":{"installerType":"WindowsInstallerMsi","asset":"","url":"https://github.com/cli/cli/releases/download/v2.88.1/gh_2.88.1_windows_arm64.msi"},"1":{"installerType":"WindowsInstallerMsi","asset":"","url":"https://github.com/cli/cli/releases/download/v2.88.1/gh_2.88.1_windows_amd64.msi"}},"install":{"win32":{"assetId":1,"exec":null,"scope":"Machine","installerArgs":null},"winarm":{"assetId":0,"exec":null,"scope":"Machine","installerArgs":null},"linux":null,"linuxArm64":null,"linuxArm7":null,"android":null},"displayImages":[],"description":"Take GitHub to the command line\n\nGitHub CLI (gh) is a command-line tool that brings pull requests, issues, GitHub Actions, and other GitHub features to your terminal, so you can do all your work in one place.\nWhat's Changed\n- Migrate Windows code signing from client secret to OIDC by @BagToad in #12911\n- Revert \"refactor: deduplicate scope error handling between api/client.go and project queries\" by @williammartin in #12914\n- Revert \"fix: clarify scope error while creating issues for projects\" by @williammartin in #12915","repo":{"author":"microsoft","repo":"winget-pkgs"},"usrVersion":"2.88.1","version":0,"site":"https://github.com/home/","source":"GitHub, Inc.","license_or_tos":"MIT","resources":null,"verified":false}