{"appId":"w:GoyalSoftech.Website2APKBuilderPro","appShortcutName":"Website 2 APK Builder Pro","appDisplayName":"Website 2 APK Builder Pro","authorId":"w:winget","releaseTagName":"winget-6.0","downloadUrls":{"0":{"installerType":"WindowsInstallerMsi","asset":"","url":""},"1":{"installerType":"WindowsInstallerMsi","asset":"","url":""}},"install":{"win32":null,"winarm":null,"linux":null,"linuxArm64":null,"linuxArm7":null,"android":null},"displayImages":[],"description":"Convert your Website or HTML5 to Android Apps.\n\n\n","repo":{"author":"microsoft","repo":"winget-pkgs"},"usrVersion":"6.0","version":0,"site":"https://websitetoapk.com/","source":"Goyal Softech Pvt. Ltd.","license_or_tos":"Proprietary","resources":null,"verified":false}