{"appId":"w:Gravitational.TeleportConnect","appShortcutName":"Winget Application","appDisplayName":"Teleport Connect","authorId":"w:winget","releaseTagName":"winget-18.1.4","downloadUrls":{"1":{"installerType":"WindowsInstallerExe","asset":"","url":"https://cdn.teleport.dev/Teleport%20Connect%20Setup-18.1.4.exe"},"0":{"installerType":"WindowsInstallerMsi","asset":"","url":""}},"install":{"win32":{"assetId":1,"exec":null,"scope":"Machine","installerArgs":null},"winarm":null,"linux":null,"linuxArm64":null,"linuxArm7":null,"android":null},"displayImages":[],"description":"Teleport Connect provides easy and secure access to SSH servers, databases, applications, Windows desktops, and Kubernetes clusters.\n\n\n- Fixed access denied error messages not being displayed in the Teleport web UI PostgreSQL client. #57568\n- Fixed a bug in the default discovery script that can happen discovering instances whose PATH doesn't contain /usr/local/bin. #57530","repo":{"author":"microsoft","repo":"winget-pkgs"},"version":"18.1.4","site":null,"source":"Gravitational, Inc.","license_or_tos":"Proprietary","resources":null,"verified":false}