{"appId":"w:hrzlgnm.mdns_browser","appShortcutName":"Winget Application","appDisplayName":"mdns-browser","authorId":"w:winget","releaseTagName":"winget-0.20.1","downloadUrls":{"0":{"installerType":"WindowsInstallerMsi","asset":"","url":""},"1":{"installerType":"WindowsInstallerExe","asset":"","url":"https://github.com/hrzlgnm/mdns-browser/releases/download/mdns-browser-v0.20.1/mdns-browser_0.20.1_x64-setup.exe"}},"install":{"win32":{"assetId":1,"exec":null,"scope":"User","installerArgs":null},"winarm":null,"linux":null,"linuxArm64":null,"linuxArm7":null,"android":null},"displayImages":[],"description":"mDNS Browser\n\nmDNS Browser\nWhat's Changed\n- #1250 chore: Add explicit conflict declarations between mdns-browser and mdns-browser-bin @hrzlgnm","repo":{"author":"microsoft","repo":"winget-pkgs"},"version":"0.20.1","site":"https://github.com/hrzlgnm","source":"hrzlgnm","license_or_tos":"MIT","resources":null,"verified":false}