{"appId":"w:Logitech.OptionsPlus","appShortcutName":"Logi Options+","appDisplayName":"Logi Options+","authorId":"w:winget","releaseTagName":"winget-1.99.834046","downloadUrls":{"0":{"installerType":"WindowsInstallerMsi","asset":"","url":""},"1":{"installerType":"WindowsInstallerExe","asset":"","url":"https://download01.logi.com/web/ftp/pub/techsupport/optionsplus/logioptionsplus_installer.exe"}},"install":{"win32":{"assetId":1,"exec":null,"scope":"Machine","installerArgs":null},"winarm":null,"linux":null,"linuxArm64":null,"linuxArm7":null,"android":null},"displayImages":[],"description":"Customization App for Logitech Devices\n\nEnhance your Logitech devices with Logi Options Plus software. Customize settings, create shortcuts, and increase productivity.\n","repo":{"author":"microsoft","repo":"winget-pkgs"},"usrVersion":"1.99.834046","version":0,"site":"https://www.logitech.com/","source":"Logitech","license_or_tos":"Proprietary","resources":null,"verified":false}