{"appId":"w:NitrokeyGmbH.Nitropy","appShortcutName":"Nitropy","appDisplayName":"Nitropy","authorId":"w:winget","releaseTagName":"winget-0.11.4","downloadUrls":{"1":{"installerType":"WindowsInstallerMsi","asset":"","url":"https://github.com/Nitrokey/pynitrokey/releases/download/v0.11.4/nitropy-v0.11.4-x64-windows-installer.msi"},"0":{"installerType":"WindowsInstallerMsi","asset":"","url":""}},"install":{"win32":{"assetId":1,"exec":null,"scope":"Machine","installerArgs":null},"winarm":null,"linux":null,"linuxArm64":null,"linuxArm7":null,"android":null},"displayImages":[],"description":"A command line interface for the Nitrokey FIDO2, Nitrokey Start, Nitrokey 3 and NetHSM.\n\n\nWhat's Changed\n- Add maintainer keys and check tag signatures in CI by @robin-nitrokey in #723\n- ci: Fetch tags for signature verification by @robin-nitrokey in #725\n- Update maintainers file by @robin-nitrokey in #724\n- Update signature key by @robin-nitrokey in #726\n- Update locked dependencies by @robin-nitrokey in #727\n- Update developer and packaging docs by @robin-nitrokey in #729\n- Add CODEOWNERS file by @robin-nitrokey in #732\n- Feat/better log file handling by @james-knippes in #733\nNew Contributors\n- @james-knippes made their first contribution in #733\nFull Changelog: v0.11.3...v0.11.4","repo":{"author":"microsoft","repo":"winget-pkgs"},"usrVersion":"0.11.4","version":0,"site":"https://github.com/Nitrokey","source":"Nitrokey GmbH","license_or_tos":"Apache-2.0","resources":null,"verified":false}