{"appId":"w:SMART.SMARTEducationSoftware","appShortcutName":"SMART Education Software","appDisplayName":"SMART Education Software","authorId":"w:winget","releaseTagName":"winget-25.1.354.1","downloadUrls":{"0":{"installerType":"WindowsInstallerMsi","asset":"","url":""},"1":{"installerType":"WindowsInstallerMsi","asset":"","url":""}},"install":{"win32":null,"winarm":null,"linux":null,"linuxArm64":null,"linuxArm7":null,"android":null},"displayImages":[],"description":"Award-winning desktop software for creating engaging learning experiences with your SMART Board®\n\n\n","repo":{"author":"microsoft","repo":"winget-pkgs"},"usrVersion":"25.1.354.1","version":0,"site":"https://www.smarttech.com/","source":"SMART Technologies ULC","license_or_tos":"Proprietary","resources":null,"verified":false}