{"appId":"w:Throneproj.Throne","appShortcutName":"Throne","appDisplayName":"Throne","authorId":"w:winget","releaseTagName":"winget-1.0.12","downloadUrls":{"0":{"installerType":"WindowsInstallerMsi","asset":"","url":""},"1":{"installerType":"WindowsInstallerExe","asset":"","url":"https://github.com/throneproj/Throne/releases/download/1.0.12/Throne-1.0.12-windows64-installer.exe"}},"install":{"win32":{"assetId":1,"exec":null,"scope":"User","installerArgs":null},"winarm":null,"linux":null,"linuxArm64":null,"linuxArm7":null,"android":null},"displayImages":[],"description":"Cross-platform GUI proxy utility (Empowered by sing-box)\n\n\n- Fix XHTTP extra parameters parsing\n- Improve Clash(Meta/mihomo) subscription support\n- Support SIP008 format subscription\n- Minor other fixes","repo":{"author":"microsoft","repo":"winget-pkgs"},"usrVersion":"1.0.12","version":0,"site":"https://github.com/throneproj","source":"Throneproj","license_or_tos":"GPL-3.0","resources":null,"verified":false}