{"appId":"w:VB_Audio.Voicemeeter","appShortcutName":"Voicemeeter","appDisplayName":"Voicemeeter","authorId":"w:winget","releaseTagName":"winget-1.1.2.2","downloadUrls":{"1":{"installerType":"WindowsInstallerMsi","asset":"","url":""},"0":{"installerType":"WindowsInstallerMsi","asset":"","url":""}},"install":{"win32":null,"winarm":null,"linux":null,"linuxArm64":null,"linuxArm7":null,"android":null},"displayImages":[],"description":"Voicemeeter is Audio Mixer Application endowed with Virtual Audio Device used as Virtual I/O to mix and manage any audio sources from or to any audio devices or applications.\n\n\n","repo":{"author":"microsoft","repo":"winget-pkgs"},"usrVersion":"1.1.2.2","version":0,"site":"https://vb-audio.com/index.htm","source":"VB-Audio Software","license_or_tos":"Donationware","resources":null,"verified":false}