{"appId":"winget_app_TeamSonarr.Sonarr","appShortcutName":"Winget Application","appDisplayName":"Sonarr","authorId":"winget","releaseTagName":"winget-4.0.6.1805","downloadUrls":{"0":{"installerType":"WindowsInstallerMsi","asset":"","url":""},"1":{"installerType":"WindowsInstallerExe","asset":"","url":"https://github.com/Sonarr/Sonarr/releases/download/v4.0.6.1805/Sonarr.main.4.0.6.1805.win-x64-installer.exe"}},"install":{"win32":{"assetId":1,"exec":null,"scope":"Machine","installerArgs":null},"winarm":null,"linux":null,"linuxArm64":null,"linuxArm7":null,"android":null},"displayImages":[],"description":"Sonarr is a PVR for Usenet and BitTorrent users. It can monitor multiple RSS feeds for new episodes of your favorite shows and will grab, sort and rename them.\n\n\nChanges\n- Translations update from Servarr Weblate by @ServarrAdmin in #6846\n- Fix SDR Files Being Parsed As HLG by @yammes08 in #6842\n- New: Genres and Images for Webhooks and Notifiarr by @markus101 in #6839\n- Fixed: Include full series title in episode search by @markus101 in #6844\n- Fixed: Manual Interaction Required with possible null series by @mynameisbogdan in #6850\n- Translations update from Servarr Weblate by @ServarrAdmin in #6853\n- New: Refresh cache for tracked queue on series add by @mynameisbogdan in #6849\n- Fixed: Ignore case for name validation in providers by @mynameisbogdan in #6857\n- Fixed: Skip invalid series paths during validation by @markus101 in #6855\n- Fixed: Improve error messaging if config file isn't formatted correctly by @markus101 in #6863\n- Ignore Grabbed from API docs by @mynameisbogdan in #6869\n- New: Add TMDB id support by @sundermann in #6867\n- Fixed: Adding series with unknown items in queue by @markus101 in #6874\n- Fixed: Importing from IMDb list by @markus101 in #6877\n- New: Ignore inaccessible folders with getting folders by @mynameisbogdan in #6879\n- New: Display stats for delete multiple series modal by @mynameisbogdan in #6880\n- Translations update from Servarr Weblate by @ServarrAdmin in #6891\n- New: Parse anime seasons with trailing number in title by @markus101 in #6888\n- New: Improve UI status when downloads cannot be imported automatically by @markus101 in #6889\n- Fixed: Exclude invalid releases from Newznab and Torznab parsers by @mynameisbogdan in #6892\n- New: Ability to select Plex Media Server from plex.tv by @markus101 in #6893\n- New: Ignore Deluge torrents without a title by @markus101 in #6894\n- Fixed: Prevent errors parsing releases in unexpected formats by @markus101 in #6897\n- Fixed: Reprocessing items that were previously blocked during importing by @markus101 in #6907\n- Fixed: Limit Queue maximum page size to 200 by @markus101 in #6904\n- Fixed: Don't use cleaned up release title for release title by @markus101 in #6911\n- Remove seriesTitle from EpisodeResource by @markus101 in #6912\n- Fixed: Use only trackable downloads in queue by @mynameisbogdan in #6919\n- Disable trim log database housekeeping task by @mynameisbogdan in #6920\n- Translations update from Servarr Weblate by @ServarrAdmin in #6916\n- Bump version to 4.0.6 by @markus101 in #6921","repo":{"author":"microsoft","repo":"winget-pkgs"},"version":"4.0.6.1805","site":"https://sonarr.tv/","source":"Team Sonarr","license_or_tos":"GPL-3.0","resources":null,"verified":false}