{"appId":"winget_app_HiroSystems.Chainhook","appShortcutName":"Winget Application","appDisplayName":"chainhook","authorId":"winget","releaseTagName":"winget-1.8.0","downloadUrls":{"0":{"installerType":"WindowsInstallerMsi","asset":"","url":""},"1":{"installerType":"WindowsInstallerMsi","asset":"","url":"https://github.com/hirosystems/chainhook/releases/download/v1.8.0/chainhook-windows-x64.msi"}},"install":{"win32":{"assetId":1,"exec":null,"scope":"Machine","installerArgs":null},"winarm":null,"linux":null,"linuxArm64":null,"linuxArm7":null,"android":null},"displayImages":[],"description":"Chainhook is a reorg-aware indexing engine for the Stacks & Bitcoin blockchains.\n\n\n","repo":{"author":"microsoft","repo":"winget-pkgs"},"version":"1.8.0","site":"https://www.hiro.so","source":"Hiro Systems","license_or_tos":"GPL-3.0","resources":null,"verified":false}