{"appId":"winget_app_monsterkodi.kappo","appShortcutName":"Winget Application","appDisplayName":"kappo","authorId":"winget","releaseTagName":"winget-1.31.0","downloadUrls":{"1":{"installerType":"WindowsInstallerExe","asset":"","url":"https://github.com/monsterkodi/kappo/releases/download/v1.31.0/kappo-1.31.0-setup.exe"},"0":{"installerType":"WindowsInstallerMsi","asset":"","url":""}},"install":{"win32":{"assetId":1,"exec":null,"scope":"Machine","installerArgs":null},"winarm":null,"linux":null,"linuxArm64":null,"linuxArm7":null,"android":null},"displayImages":[],"description":"application launcher\n\n\n","repo":{"author":"microsoft","repo":"winget-pkgs"},"version":"1.31.0","site":"https://github.com/monsterkodi","source":"monsterkodi","license_or_tos":"copyright (c) monsterkodi","resources":null,"verified":false}