{"appId":"winget_app_CongusBongus.CDogsSDL","appShortcutName":"Winget Application","appDisplayName":"C-Dogs SDL","authorId":"winget","releaseTagName":"winget-1.5.0","downloadUrls":{"1":{"installerType":"WindowsInstallerMsi","asset":"","url":""},"0":{"installerType":"WindowsInstallerMsi","asset":"","url":""}},"install":{"win32":null,"winarm":null,"linux":null,"linuxArm64":null,"linuxArm7":null,"android":null},"displayImages":[],"description":"C-Dogs SDL is a classic overhead run-and-gun game, supporting up to 4 players in co-op and deathmatch modes. Customize your player, choose from many weapons, and blast, slide and slash your way through over 100 user-created campaigns. Have fun!\n\n\n- Remove quick play #762\n- Fix weapons being picked up into incorrect slots #781 (@Kurtsley, raised by @PavanLuca)\n- Fix grenades not persisting across levels #788 (raised by @PavanLuca)\n- Fix bullets not falling\n- Fix unable to start game with co-op AI, stuck in weapon menu\n- Fix or replace many files with missing or problematic licenses (@reinerh)\n- Fix duplicate brass shells #774 (@Kurtsley, raised by @PavanLuca)\n- Fix poison grenade icon #795 (raised by @PavanLuca)\n- Fix incorrect zapper spritesheet #796 (raised by @PavanLuca)\n- Fix missing music error message #775 (raised by @PavanLuca)\n- Improve character customization by separating hats, hair, facial hair and glasses #601\n- Improve controls info by renaming button1/button2 to fire/switch #725 (@Kurtsley)","repo":{"author":"microsoft","repo":"winget-pkgs"},"version":"1.5.0","site":"https://github.com/cxong/cdogs-sdl","source":"C-Dogs SDL Team","license_or_tos":"GPL-2.0","resources":null,"verified":false}