{"appId":"winget_app_Suwayomi.Tachidesk_Sorayomi","appShortcutName":"Winget Application","appDisplayName":"Tachidesk Sorayomi","authorId":"winget","releaseTagName":"winget-0.5.23","downloadUrls":{"1":{"installerType":"WindowsInstallerMsi","asset":"","url":"https://github.com/Suwayomi/Tachidesk-Sorayomi/releases/download/0.5.23/tachidesk-sorayomi-0.5.23-windows-x64.msi"},"0":{"installerType":"WindowsInstallerMsi","asset":"","url":""}},"install":{"win32":{"assetId":1,"exec":null,"scope":"Machine","installerArgs":null},"winarm":null,"linux":null,"linuxArm64":null,"linuxArm7":null,"android":null},"displayImages":[],"description":"A free and open source manga reader based on Flutter to read manga from a Tachidesk-Server instance.\n\n\nWhat's Changed\n- Updated iOS & macOS icons\n- Added quick search toggle\n- fixed update pop up screen freeze\nCommits\n- fixed ios, macos icons by @DattatreyaReddy in #274\n- Windows fix by @DattatreyaReddy in #275","repo":{"author":"microsoft","repo":"winget-pkgs"},"version":"0.5.23","site":"https://github.com/Suwayomi","source":"Suwayomi","license_or_tos":"MPL-2.0","resources":null,"verified":false}