{"appId":"winget_app_Tencent.QQMusic","appShortcutName":"Winget Application","appDisplayName":"QQ Music","authorId":"winget","releaseTagName":"winget-21.11","downloadUrls":{"0":{"installerType":"WindowsInstallerMsi","asset":"","url":""},"1":{"installerType":"WindowsInstallerExe","asset":"","url":"https://dldir1v6.qq.com/music/clntupate/QQMusic_Setup_2111.exe"}},"install":{"win32":{"assetId":1,"exec":null,"scope":"Machine","installerArgs":null},"winarm":null,"linux":null,"linuxArm64":null,"linuxArm7":null,"android":null},"displayImages":[],"description":"A free music service by Tencent\n\nQQ Music is an online music platform by Tencent that is the leading genuine digital music service on the China's Internet, as well as a free music player which is always walking in the forefront of the music trends and provides users with smooth online music listening experience and splendid music community services.\nIt provides unlimited songs online audition, karaoke lyrics mode, online debut of popular new songs and useful music management.\nPremium users can also enjoy privileges such as high-definition music audition, genuine music download, free background music for personal homepage, music videos, etc.\nIf you have QQ Music Player, you will have your own popular music!\n","repo":{"author":"microsoft","repo":"winget-pkgs"},"version":"21.11","site":"https://y.qq.com/","source":"腾讯科技（深圳）有限公司","license_or_tos":"Proprietary","resources":null,"verified":false}