{"appId":"winget_app_Henry++.simplewall","appShortcutName":"Winget Application","appDisplayName":"simplewall","authorId":"winget","releaseTagName":"winget-3.8.5","downloadUrls":{"1":{"installerType":"WindowsInstallerMsi","asset":"","url":""},"0":{"installerType":"WindowsInstallerMsi","asset":"","url":""}},"install":{"win32":null,"winarm":null,"linux":null,"linuxArm64":null,"linuxArm7":null,"android":null},"displayImages":[],"description":"Simple tool to configure Windows Filtering Platform (WFP) which can configure network activity on your computer.\n\n\nThis is a maintenance release.\n- fixed adding apps with drive letters instead of specific apps (issue #1887)\n- fixed creating rules for inaccessible paths (issue #1891)\n- fixed opening log with spaces path (issue #1912)\n- fixed windows 7 loopback rules\n- cosmetic fixes","repo":{"author":"microsoft","repo":"winget-pkgs"},"version":"3.8.5","site":"https://github.com/henrypp/","source":"Henry++","license_or_tos":"GPL-3.0","resources":null,"verified":false}