{"appId":"w:Xiaoe.Xiaoetong","appShortcutName":"小鹅通助手","appDisplayName":"小鹅通助手","authorId":"w:winget","releaseTagName":"winget-1.10.40","downloadUrls":{"1":{"installerType":"WindowsInstallerMsi","asset":"","url":""},"0":{"installerType":"WindowsInstallerMsi","asset":"","url":""}},"install":{"win32":null,"winarm":null,"linux":null,"linuxArm64":null,"linuxArm7":null,"android":null},"displayImages":[],"description":"A PC client for Xiaoetong instructors to conduct live streaming\n\nXiaoetong Assistant is a PC client for Xiaoetong instructors to conduct live streaming.\nIt is suitable for scenarios that require webcams, slide presentation, drawing, screen sharing, and real-time video communication with students.\n","repo":{"author":"microsoft","repo":"winget-pkgs"},"usrVersion":"1.10.40","version":0,"site":"https://www.xiaoe-tech.com","source":"Shenzhen Goose Network Technology Co., Ltd.","license_or_tos":"Proprietary","resources":null,"verified":false}