{"appId":"w:ZugferdCommunity.QubaViewer","appShortcutName":"Quba","appDisplayName":"Quba","authorId":"w:winget","releaseTagName":"winget-1.5.1","downloadUrls":{"0":{"installerType":"WindowsInstallerMsi","asset":"","url":""},"1":{"installerType":"WindowsInstallerMsi","asset":"","url":"https://github.com/ZUGFeRD/quba-viewer/releases/download/v1.5.1/Quba.1.5.1.msi"}},"install":{"win32":{"assetId":1,"exec":null,"scope":"User","installerArgs":null},"winarm":null,"linux":null,"linuxArm64":null,"linuxArm7":null,"android":null},"displayImages":[],"description":"Quba is a viewer for electronic invoices\n\nQuba-Viewer is a cross platform open source application to display structured (i.e., XML) and hybrid (Factur-X/ZUGFeRD PDF) electronic invoices.\nFixes\n- updated electron and form-data packages (#154)\n- fix window management for MacOS (#155)\n- #156 fix double apostrophe characters\n- #27 multiple discounts per line item (BT-147)\n- #29 fix attachment preview (images/PDFs)\n- #49 fix date not displayed (BT-72)\n- #134 fix BT-72 (contributed by SemikolonDEV)\n- #93 translation not switched completely on runtime","repo":{"author":"microsoft","repo":"winget-pkgs"},"usrVersion":"1.5.1","version":0,"site":"https://quba-viewer.org/","source":"Quba","license_or_tos":"Apache-2.0","resources":null,"verified":false}